Sugar_Honey_IceTea/__init__.py
Sugar_Honey_IceTea/add.py
Sugar_Honey_IceTea/power.py
Sugar_Honey_IceTea/subtract.py
Sugar_Honey_IceTea/extras/__init__.py
Sugar_Honey_IceTea/extras/divide.py
Sugar_Honey_IceTea/extras/multiply.py
Sugar_Honey_IceTea-0.0.69.dist-info/METADATA
Sugar_Honey_IceTea-0.0.69.dist-info/WHEEL
Sugar_Honey_IceTea-0.0.69.dist-info/top_level.txt
Sugar_Honey_IceTea-0.0.69.dist-info/RECORD
